<parameters>
<query id="26" grammar="data/en-ar.trec02/cdec.grammar/grammar.25">Kurdistan Independence</query>
<query id="27" grammar="data/en-ar.trec02/cdec.grammar/grammar.26">Iranian and Iraqi P.O.W.'s</query>
<query id="28" grammar="data/en-ar.trec02/cdec.grammar/grammar.27">Hazardous waste disposal</query>
<query id="29" grammar="data/en-ar.trec02/cdec.grammar/grammar.28">Saudi Internet Service Providers</query>
<query id="30" grammar="data/en-ar.trec02/cdec.grammar/grammar.29">Iraqi Satellite Television</query>
<query id="31" grammar="data/en-ar.trec02/cdec.grammar/grammar.30">Trade Integration</query>
<query id="32" grammar="data/en-ar.trec02/cdec.grammar/grammar.31">Caspian Beluga Conservation</query>
<query id="33" grammar="data/en-ar.trec02/cdec.grammar/grammar.32">Suez Canal Traffic</query>
<query id="34" grammar="data/en-ar.trec02/cdec.grammar/grammar.33">Agricultural Development project</query>
<query id="35" grammar="data/en-ar.trec02/cdec.grammar/grammar.34">Mina Sulman/Umm Qasr Sea Link</query>
<query id="36" grammar="data/en-ar.trec02/cdec.grammar/grammar.35">'Oil for Food' program</query>
<query id="37" grammar="data/en-ar.trec02/cdec.grammar/grammar.36">Beirut Film Festival</query>
<query id="38" grammar="data/en-ar.trec02/cdec.grammar/grammar.37">Traditional Arab Arts</query>
<query id="39" grammar="data/en-ar.trec02/cdec.grammar/grammar.38">Jerash Festival Critics</query>
<query id="40" grammar="data/en-ar.trec02/cdec.grammar/grammar.39">Iranian Caspian Access</query>
<query id="41" grammar="data/en-ar.trec02/cdec.grammar/grammar.40">Meningitis Vaccine Access</query>
<query id="42" grammar="data/en-ar.trec02/cdec.grammar/grammar.41">Sadeq al-Sadr Assassination</query>
<query id="43" grammar="data/en-ar.trec02/cdec.grammar/grammar.42">Child/Motherhood Welfare Society</query>
<query id="44" grammar="data/en-ar.trec02/cdec.grammar/grammar.43">Gaza International Airport</query>
<query id="45" grammar="data/en-ar.trec02/cdec.grammar/grammar.44">Wye River Agreement</query>
<query id="46" grammar="data/en-ar.trec02/cdec.grammar/grammar.45">Lahoud's Presidential Victory</query>
<query id="47" grammar="data/en-ar.trec02/cdec.grammar/grammar.46">European Union Expansion</query>
<query id="48" grammar="data/en-ar.trec02/cdec.grammar/grammar.47">Refugees in Zaire</query>
<query id="49" grammar="data/en-ar.trec02/cdec.grammar/grammar.48">Earthquake in Turkey</query>
<query id="50" grammar="data/en-ar.trec02/cdec.grammar/grammar.49">Transnational Muslim Brotherhood</query>
<query id="51" grammar="data/en-ar.trec02/cdec.grammar/grammar.50">Personal Status Law.</query>
<query id="52" grammar="data/en-ar.trec02/cdec.grammar/grammar.51">Nile Basin Initiative</query>
<query id="53" grammar="data/en-ar.trec02/cdec.grammar/grammar.52">Tunisian Urban Transport</query>
<query id="54" grammar="data/en-ar.trec02/cdec.grammar/grammar.53">Blue Nile Dam</query>
<query id="55" grammar="data/en-ar.trec02/cdec.grammar/grammar.54">Umm Kalthoum's Influence</query>
<query id="56" grammar="data/en-ar.trec02/cdec.grammar/grammar.55">Indo-Pakistani Political Instability</query>
<query id="57" grammar="data/en-ar.trec02/cdec.grammar/grammar.56">Palestinian Students, Israeli Schools</query>
<query id="58" grammar="data/en-ar.trec02/cdec.grammar/grammar.57">Pan Am Lockerbie Negotiations</query>
<query id="59" grammar="data/en-ar.trec02/cdec.grammar/grammar.58">Bosnian War Crimes Tribunal</query>
<query id="60" grammar="data/en-ar.trec02/cdec.grammar/grammar.59">Microsoft Anti-trust Case</query>
<query id="61" grammar="data/en-ar.trec02/cdec.grammar/grammar.60">Southern Lebanon, Israeli Retaliation</query>
<query id="62" grammar="data/en-ar.trec02/cdec.grammar/grammar.61">Netanyahu's re-election campaign</query>
<query id="63" grammar="data/en-ar.trec02/cdec.grammar/grammar.62">Changes, Russian Constitution</query>
<query id="64" grammar="data/en-ar.trec02/cdec.grammar/grammar.63">security measures, sporting events</query>
<query id="65" grammar="data/en-ar.trec02/cdec.grammar/grammar.64">Mad Cow and EU</query>
<query id="66" grammar="data/en-ar.trec02/cdec.grammar/grammar.65">Arab countries and mad cow</query>
<query id="67" grammar="data/en-ar.trec02/cdec.grammar/grammar.66">Clinton and Camp David talks</query>
<query id="68" grammar="data/en-ar.trec02/cdec.grammar/grammar.67">AlFayed, Dodi and Diana's deaths</query>
<query id="69" grammar="data/en-ar.trec02/cdec.grammar/grammar.68">Mir returns to earth</query>
<query id="70" grammar="data/en-ar.trec02/cdec.grammar/grammar.69">bin Laden Targets U.S.</query>
<query id="71" grammar="data/en-ar.trec02/cdec.grammar/grammar.70">The Pope in Palestine</query>
<query id="72" grammar="data/en-ar.trec02/cdec.grammar/grammar.71">NATO, Serbo-Kosovar Conflict</query>
<query id="73" grammar="data/en-ar.trec02/cdec.grammar/grammar.72">Chechnyan Attacks against Russia</query>
<query id="74" grammar="data/en-ar.trec02/cdec.grammar/grammar.73">Year 2000 bug</query>
<query id="75" grammar="data/en-ar.trec02/cdec.grammar/grammar.74">Computer viruses in Arab world</query>
</parameters>
